fadge/__init__.py
fadge/__main__.py
fadge/bounds.py
fadge/core.py
fadge/geode.py
fadge/icond.py
fadge/metric.py
fadge/shadow.py
fadge/utils.py
fadge/viz.py
fadge-0.1.7.dist-info/LICENSE
fadge-0.1.7.dist-info/METADATA
fadge-0.1.7.dist-info/WHEEL
fadge-0.1.7.dist-info/entry_points.txt
fadge-0.1.7.dist-info/top_level.txt
fadge-0.1.7.dist-info/RECORD
