Metadata-Version: 2.1
Name: fadge
Version: 0.1.7
Summary: Fast Automatic Differential GEometry
Home-page: https://github.com/adxsrc/fadge
Author: Chi-kwan Chan
Author-email: chanc@arizona.edu
Requires-Python: >=3.7,<3.12
License-File: LICENSE
Requires-Dist: xaj <0.2,>=0.1.8
Requires-Dist: click >=7.1.2
Requires-Dist: h5py >=3
